edison/__init__.py
edison_ml-0.1.0.data/scripts/edi
edison_ml-0.1.0.dist-info/DESCRIPTION.rst
edison_ml-0.1.0.dist-info/METADATA
edison_ml-0.1.0.dist-info/RECORD
edison_ml-0.1.0.dist-info/WHEEL
edison_ml-0.1.0.dist-info/metadata.json
edison_ml-0.1.0.dist-info/top_level.txt
