Metadata-Version: 2.0
Name: edison-ml
Version: 0.1.0
Summary: simple machine learning pipeline toolkit
Home-page: https://github.com/jiangplus/edison
Author: jiangplus
Author-email: jiang.plus.times@gmail.com
License: UNKNOWN
Platform: UNKNOWN
Classifier: Programming Language :: Python :: 3
Classifier: License :: OSI Approved :: MIT License
Classifier: Operating System :: OS Independent
Requires-Python: >=3.6
